{"aruba":"oranjestad","afghanistan":"kabul","angola":"luanda","anguilla":"the_valley","åland_islands":"mariehamn","albania":"tirana","andorra":"andorra_la_vella","united_arab_emirates":"abu_dhabi","argentina":"buenos_aires","armenia":"yerevan","american_samoa":"pago_pago","french_southern_and_antarctic_lands":"port-aux-français","antigua_and_barbuda":"saint_john's","australia":"canberra","austria":"vienna","azerbaijan":"baku","burundi":"gitega","belgium":"brussels","benin":"porto-novo","burkina_faso":"ouagadougou","bangladesh":"dhaka","bulgaria":"sofia","bahrain":"manama","bahamas":"nassau","bosnia_and_herzegovina":"sarajevo","saint_barthélemy":"gustavia","saint_helena,_ascension_and_tristan_da_cunha":"jamestown","belarus":"minsk","belize":"belmopan","bermuda":"hamilton","bolivia":"sucre","brazil":"brasília","barbados":"bridgetown","brunei":"bandar_seri_begawan","bhutan":"thimphu","botswana":"gaborone","central_african_republic":"bangui","canada":"ottawa","cocos_(keeling)_islands":"west_island","switzerland":"bern","chile":"santiago","china":"beijing","ivory_coast":"yamoussoukro","cameroon":"yaoundé","dr_congo":"kinshasa","republic_of_the_congo":"brazzaville","cook_islands":"avarua","colombia":"bogotá","comoros":"moroni","cape_verde":"praia","costa_rica":"san_josé","cuba":"havana","curaçao":"willemstad","christmas_island":"flying_fish_cove","cayman_islands":"george_town","cyprus":"nicosia","czechia":"prague","germany":"berlin","djibouti":"djibouti","dominica":"roseau","denmark":"copenhagen","dominican_republic":"santo_domingo","algeria":"algiers","ecuador":"quito","egypt":"cairo","eritrea":"asmara","western_sahara":"el_aaiún","spain":"madrid","estonia":"tallinn","ethiopia":"addis_ababa","finland":"helsinki","fiji":"suva","falkland_islands":"stanley","france":"paris","faroe_islands":"tórshavn","micronesia":"palikir","gabon":"libreville","united_kingdom":"london","georgia":"tbilisi","guernsey":"st._peter_port","ghana":"accra","gibraltar":"gibraltar","guinea":"conakry","guadeloupe":"basse-terre","gambia":"banjul","guinea-bissau":"bissau","equatorial_guinea":"malabo","greece":"athens","grenada":"st._george's","greenland":"nuuk","guatemala":"guatemala_city","french_guiana":"cayenne","guam":"hagåtña","guyana":"georgetown","hong_kong":"city_of_victoria","honduras":"tegucigalpa","croatia":"zagreb","haiti":"port-au-prince","hungary":"budapest","indonesia":"jakarta","isle_of_man":"douglas","india":"new_delhi","british_indian_ocean_territory":"diego_garcia","ireland":"dublin","iran":"tehran","iraq":"baghdad","iceland":"reykjavik","israel":"jerusalem","italy":"rome","jamaica":"kingston","jersey":"saint_helier","jordan":"amman","japan":"tokyo","kazakhstan":"nur-sultan","kenya":"nairobi","kyrgyzstan":"bishkek","cambodia":"phnom_penh","kiribati":"south_tarawa","saint_kitts_and_nevis":"basseterre","south_korea":"seoul","kosovo":"pristina","kuwait":"kuwait_city","laos":"vientiane","lebanon":"beirut","liberia":"monrovia","libya":"tripoli","saint_lucia":"castries","liechtenstein":"vaduz","sri_lanka":"colombo","lesotho":"maseru","lithuania":"vilnius","luxembourg":"luxembourg","latvia":"riga","saint_martin":"marigot","morocco":"rabat","monaco":"monaco","moldova":"chișinău","madagascar":"antananarivo","maldives":"malé","mexico":"mexico_city","marshall_islands":"majuro","north_macedonia":"skopje","mali":"bamako","malta":"valletta","myanmar":"naypyidaw","montenegro":"podgorica","mongolia":"ulan_bator","northern_mariana_islands":"saipan","mozambique":"maputo","mauritania":"nouakchott","montserrat":"plymouth","martinique":"fort-de-france","mauritius":"port_louis","malawi":"lilongwe","malaysia":"kuala_lumpur","mayotte":"mamoudzou","namibia":"windhoek","new_caledonia":"nouméa","niger":"niamey","norfolk_island":"kingston","nigeria":"abuja","nicaragua":"managua","niue":"alofi","netherlands":"amsterdam","norway":"oslo","nepal":"kathmandu","nauru":"yaren","new_zealand":"wellington","oman":"muscat","pakistan":"islamabad","panama":"panama_city","pitcairn_islands":"adamstown","peru":"lima","philippines":"manila","palau":"ngerulmud","papua_new_guinea":"port_moresby","poland":"warsaw","puerto_rico":"san_juan","north_korea":"pyongyang","portugal":"lisbon","paraguay":"asunción","palestine":"ramallah","french_polynesia":"papeetē","qatar":"doha","réunion":"saint-denis","romania":"bucharest","russia":"moscow","rwanda":"kigali","saudi_arabia":"riyadh","sudan":"khartoum","senegal":"dakar","singapore":"singapore","south_georgia":"king_edward_point","svalbard_and_jan_mayen":"longyearbyen","solomon_islands":"honiara","sierra_leone":"freetown","el_salvador":"san_salvador","san_marino":"city_of_san_marino","somalia":"mogadishu","saint_pierre_and_miquelon":"saint-pierre","serbia":"belgrade","south_sudan":"juba","são_tomé_and_príncipe":"são_tomé","suriname":"paramaribo","slovakia":"bratislava","slovenia":"ljubljana","sweden":"stockholm","eswatini":"lobamba","sint_maarten":"philipsburg","seychelles":"victoria","syria":"damascus","turks_and_caicos_islands":"cockburn_town","chad":"n'djamena","togo":"lomé","thailand":"bangkok","tajikistan":"dushanbe","tokelau":"fakaofo","turkmenistan":"ashgabat","timor-leste":"dili","tonga":"nuku'alofa","trinidad_and_tobago":"port_of_spain","tunisia":"tunis","turkey":"ankara","tuvalu":"funafuti","taiwan":"taipei","tanzania":"dodoma","uganda":"kampala","ukraine":"kyiv","uruguay":"montevideo","united_states":"new_york","uzbekistan":"tashkent","vatican_city":"vatican_city","saint_vincent_and_the_grenadines":"kingstown","venezuela":"caracas","british_virgin_islands":"road_town","united_states_virgin_islands":"charlotte_amalie","vietnam":"hanoi","vanuatu":"port_vila","wallis_and_futuna":"mata-utu","samoa":"apia","yemen":"sana'a","south_africa":"pretoria","zambia":"lusaka","zimbabwe":"harare","usa":"new_york","britain":"london"}